rfi_fileparser/__init__.py
rfi_fileparser/downloader.py
rfi_fileparser/events.py
rfi_fileparser/heatmap.py
rfi_fileparser/util.py
rfi_fileparser/.idea/.gitignore
rfi_fileparser/.idea/.name
rfi_fileparser/.idea/RFI_FileParser.iml
rfi_fileparser/.idea/misc.xml
rfi_fileparser/.idea/modules.xml
rfi_fileparser/.idea/vcs.xml
rfi_fileparser/.idea/workspace.xml
rfi_fileparser/.idea/inspectionProfiles/profiles_settings.xml
rfi_fileparser-0.6.2.dist-info/METADATA
rfi_fileparser-0.6.2.dist-info/WHEEL
rfi_fileparser-0.6.2.dist-info/licenses/LICENSE
rfi_fileparser-0.6.2.dist-info/RECORD
