Metadata-Version: 2.4
Name: rfi_fileparser
Version: 0.6.2
Summary: Python tools to download JSON files from rfi.stanford.edu.
Author-email: Zixi Liu <liu1322@stanford.edu>
License: MIT
License-File: LICENSE
Requires-Python: >=3.8
Requires-Dist: contextily
Requires-Dist: geopandas
Requires-Dist: h3==3.7.6
Requires-Dist: matplotlib
Requires-Dist: pandas
Requires-Dist: requests
Requires-Dist: shapely
